jinjer
