Metadata-Version: 1.0
Name: jinjer
Version: 0.3
Summary: Tool to render Jinja templates from command line
Home-page: https://github.com/andrematheus/jinjer
Author: André Roque Matheus
Author-email: amatheus@ligandoospontos.com.br
License: BSD
Platform: UNKNOWN
